build
dist
examples
mpoints
napiod
paper
tests
tutorials
